{
  "after_0000": {
    "E35": 1,
    "E36": 1,
    "R33": 1
  },
  "at_hospital_count": {},
  "calls": {
    "D35": 2,
    "E34": 5,
    "E35": 2,
    "E36": 9,
    "LR36": 1,
    "R33": 10,
    "R34": 8,
    "R35": 2,
    "R36": 5,
    "S36": 2,
    "T33": 5
  },
  "dur_sec": {},
  "duration_known_calls": {
    "D35": 0,
    "E34": 0,
    "E35": 0,
    "E36": 0,
    "LR36": 0,
    "R33": 0,
    "R34": 0,
    "R35": 0,
    "R36": 0,
    "S36": 0,
    "T33": 0
  },
  "max_sec": {},
  "ride_in_count": {
    "D35": 0,
    "E34": 0,
    "E35": 0,
    "E36": 0,
    "LR36": 0,
    "R33": 0,
    "R34": 0,
    "R35": 0,
    "R36": 0,
    "S36": 0,
    "T33": 0
  },
  "transporting_count": {}
}