{
  "generated_at": "2026-01-05T09:41:16.797275-05:00",
  "month": {
    "end_date": "2026-01-05",
    "start_date": "2025-12-07",
    "units": {
      "D35": {
        "avg_call_duration_mins": 15.52,
        "highest_call_duration_mins": 63.33,
        "single_shift_max_after_midnight": 2,
        "single_shift_max_calls": 4,
        "total_calls": 38,
        "total_calls_after_midnight": 6
      },
      "E33": {
        "avg_call_duration_mins": 0.75,
        "highest_call_duration_mins": 0.73,
        "single_shift_max_after_midnight": 0,
        "single_shift_max_calls": 1,
        "total_calls": 1,
        "total_calls_after_midnight": 0
      },
      "E34": {
        "avg_call_duration_mins": 14.48,
        "highest_call_duration_mins": 99.67,
        "single_shift_max_after_midnight": 4,
        "single_shift_max_calls": 10,
        "total_calls": 153,
        "total_calls_after_midnight": 15
      },
      "E35": {
        "avg_call_duration_mins": 18.29,
        "highest_call_duration_mins": 132.0,
        "single_shift_max_after_midnight": 4,
        "single_shift_max_calls": 10,
        "total_calls": 202,
        "total_calls_after_midnight": 42
      },
      "E36": {
        "avg_call_duration_mins": 18.97,
        "highest_call_duration_mins": 107.53,
        "single_shift_max_after_midnight": 3,
        "single_shift_max_calls": 10,
        "total_calls": 189,
        "total_calls_after_midnight": 24
      },
      "LR36": {
        "avg_call_duration_mins": 19.87,
        "highest_call_duration_mins": 79.38,
        "single_shift_max_after_midnight": 2,
        "single_shift_max_calls": 7,
        "total_calls": 57,
        "total_calls_after_midnight": 6
      },
      "R33": {
        "avg_call_duration_mins": 16.48,
        "highest_call_duration_mins": 101.63,
        "single_shift_max_after_midnight": 5,
        "single_shift_max_calls": 17,
        "total_calls": 251,
        "total_calls_after_midnight": 30
      },
      "R34": {
        "avg_call_duration_mins": 16.96,
        "highest_call_duration_mins": 88.82,
        "single_shift_max_after_midnight": 4,
        "single_shift_max_calls": 14,
        "total_calls": 236,
        "total_calls_after_midnight": 40
      },
      "S36": {
        "avg_call_duration_mins": 16.62,
        "highest_call_duration_mins": 134.02,
        "single_shift_max_after_midnight": 3,
        "single_shift_max_calls": 14,
        "total_calls": 202,
        "total_calls_after_midnight": 24
      },
      "T33": {
        "avg_call_duration_mins": 15.84,
        "highest_call_duration_mins": 104.33,
        "single_shift_max_after_midnight": 2,
        "single_shift_max_calls": 9,
        "total_calls": 141,
        "total_calls_after_midnight": 7
      }
    }
  },
  "prior_shift": {
    "shift_date": "2026-01-04",
    "units": {
      "E34": {
        "avg_time_on_call_mins": 4.95,
        "calls": 3,
        "calls_after_midnight": 0,
        "highest_time_on_call_mins": 14.83
      },
      "E35": {
        "avg_time_on_call_mins": 28.12,
        "calls": 10,
        "calls_after_midnight": 3,
        "highest_time_on_call_mins": 98.95
      },
      "E36": {
        "avg_time_on_call_mins": 13.91,
        "calls": 9,
        "calls_after_midnight": 2,
        "highest_time_on_call_mins": 47.07
      },
      "LR36": {
        "avg_time_on_call_mins": 10.75,
        "calls": 2,
        "calls_after_midnight": 0,
        "highest_time_on_call_mins": 16.12
      },
      "R33": {
        "avg_time_on_call_mins": 18.85,
        "calls": 6,
        "calls_after_midnight": 0,
        "highest_time_on_call_mins": 53.8
      },
      "R34": {
        "avg_time_on_call_mins": 6.56,
        "calls": 13,
        "calls_after_midnight": 4,
        "highest_time_on_call_mins": 32.23
      },
      "S36": {
        "avg_time_on_call_mins": 4.49,
        "calls": 9,
        "calls_after_midnight": 2,
        "highest_time_on_call_mins": 18.18
      },
      "T33": {
        "avg_time_on_call_mins": 13.83,
        "calls": 7,
        "calls_after_midnight": 1,
        "highest_time_on_call_mins": 26.88
      }
    }
  },
  "shift_hour_local": 7,
  "timezone": "Eastern Standard Time",
  "today": {
    "shift_date": "2026-01-05",
    "units": {
      "E34": {
        "avg_time_on_call_mins": 20.92,
        "calls": 1,
        "calls_after_midnight": 0,
        "highest_time_on_call_mins": 20.92
      },
      "E36": {
        "avg_time_on_call_mins": 0.0,
        "calls": 1,
        "calls_after_midnight": 0,
        "highest_time_on_call_mins": 0.0
      },
      "R33": {
        "avg_time_on_call_mins": 0.0,
        "calls": 1,
        "calls_after_midnight": 0,
        "highest_time_on_call_mins": 0.0
      },
      "R34": {
        "avg_time_on_call_mins": 18.51,
        "calls": 2,
        "calls_after_midnight": 0,
        "highest_time_on_call_mins": 37.02
      },
      "S36": {
        "avg_time_on_call_mins": 0.0,
        "calls": 1,
        "calls_after_midnight": 0,
        "highest_time_on_call_mins": 0.0
      }
    }
  },
  "week": {
    "end_date": "2026-01-05",
    "start_date": "2025-12-30",
    "units": {
      "D35": {
        "avg_call_duration_mins": 23.75,
        "highest_call_duration_mins": 63.33,
        "single_shift_max_after_midnight": 1,
        "single_shift_max_calls": 3,
        "total_calls": 11,
        "total_calls_after_midnight": 1
      },
      "E34": {
        "avg_call_duration_mins": 15.37,
        "highest_call_duration_mins": 64.63,
        "single_shift_max_after_midnight": 4,
        "single_shift_max_calls": 10,
        "total_calls": 26,
        "total_calls_after_midnight": 6
      },
      "E35": {
        "avg_call_duration_mins": 18.33,
        "highest_call_duration_mins": 98.95,
        "single_shift_max_after_midnight": 4,
        "single_shift_max_calls": 10,
        "total_calls": 46,
        "total_calls_after_midnight": 14
      },
      "E36": {
        "avg_call_duration_mins": 16.75,
        "highest_call_duration_mins": 74.7,
        "single_shift_max_after_midnight": 2,
        "single_shift_max_calls": 9,
        "total_calls": 39,
        "total_calls_after_midnight": 6
      },
      "LR36": {
        "avg_call_duration_mins": 18.42,
        "highest_call_duration_mins": 47.1,
        "single_shift_max_after_midnight": 2,
        "single_shift_max_calls": 7,
        "total_calls": 18,
        "total_calls_after_midnight": 3
      },
      "R33": {
        "avg_call_duration_mins": 19.65,
        "highest_call_duration_mins": 86.85,
        "single_shift_max_after_midnight": 2,
        "single_shift_max_calls": 10,
        "total_calls": 44,
        "total_calls_after_midnight": 5
      },
      "R34": {
        "avg_call_duration_mins": 12.04,
        "highest_call_duration_mins": 88.25,
        "single_shift_max_after_midnight": 4,
        "single_shift_max_calls": 13,
        "total_calls": 47,
        "total_calls_after_midnight": 12
      },
      "S36": {
        "avg_call_duration_mins": 15.81,
        "highest_call_duration_mins": 134.02,
        "single_shift_max_after_midnight": 3,
        "single_shift_max_calls": 9,
        "total_calls": 39,
        "total_calls_after_midnight": 6
      },
      "T33": {
        "avg_call_duration_mins": 14.62,
        "highest_call_duration_mins": 61.93,
        "single_shift_max_after_midnight": 1,
        "single_shift_max_calls": 8,
        "total_calls": 37,
        "total_calls_after_midnight": 3
      }
    }
  },
  "year": {
    "end_date": "2026-01-05",
    "start_date": "2025-01-06",
    "units": {
      "D35": {
        "avg_call_duration_mins": 16.0,
        "highest_call_duration_mins": 64.52,
        "single_shift_max_after_midnight": 2,
        "single_shift_max_calls": 6,
        "total_calls": 71,
        "total_calls_after_midnight": 9
      },
      "E33": {
        "avg_call_duration_mins": 0.75,
        "highest_call_duration_mins": 0.73,
        "single_shift_max_after_midnight": 0,
        "single_shift_max_calls": 1,
        "total_calls": 1,
        "total_calls_after_midnight": 0
      },
      "E34": {
        "avg_call_duration_mins": 15.49,
        "highest_call_duration_mins": 109.68,
        "single_shift_max_after_midnight": 6,
        "single_shift_max_calls": 11,
        "total_calls": 264,
        "total_calls_after_midnight": 28
      },
      "E35": {
        "avg_call_duration_mins": 15.8,
        "highest_call_duration_mins": 132.0,
        "single_shift_max_after_midnight": 5,
        "single_shift_max_calls": 18,
        "total_calls": 356,
        "total_calls_after_midnight": 73
      },
      "E36": {
        "avg_call_duration_mins": 17.41,
        "highest_call_duration_mins": 107.53,
        "single_shift_max_after_midnight": 4,
        "single_shift_max_calls": 11,
        "total_calls": 336,
        "total_calls_after_midnight": 42
      },
      "LR36": {
        "avg_call_duration_mins": 19.2,
        "highest_call_duration_mins": 79.38,
        "single_shift_max_after_midnight": 2,
        "single_shift_max_calls": 7,
        "total_calls": 104,
        "total_calls_after_midnight": 13
      },
      "R33": {
        "avg_call_duration_mins": 18.55,
        "highest_call_duration_mins": 101.63,
        "single_shift_max_after_midnight": 5,
        "single_shift_max_calls": 17,
        "total_calls": 449,
        "total_calls_after_midnight": 61
      },
      "R34": {
        "avg_call_duration_mins": 16.18,
        "highest_call_duration_mins": 210.62,
        "single_shift_max_after_midnight": 5,
        "single_shift_max_calls": 18,
        "total_calls": 462,
        "total_calls_after_midnight": 81
      },
      "R35": {
        "avg_call_duration_mins": 11.2,
        "highest_call_duration_mins": 33.58,
        "single_shift_max_after_midnight": 0,
        "single_shift_max_calls": 3,
        "total_calls": 3,
        "total_calls_after_midnight": 0
      },
      "S36": {
        "avg_call_duration_mins": 16.38,
        "highest_call_duration_mins": 134.02,
        "single_shift_max_after_midnight": 3,
        "single_shift_max_calls": 14,
        "total_calls": 350,
        "total_calls_after_midnight": 41
      },
      "T33": {
        "avg_call_duration_mins": 15.77,
        "highest_call_duration_mins": 104.33,
        "single_shift_max_after_midnight": 4,
        "single_shift_max_calls": 10,
        "total_calls": 251,
        "total_calls_after_midnight": 17
      }
    }
  }
}