{
  "generated_at": "2026-02-01T10:41:27.142528-05:00",
  "month": {
    "end_date": "2026-02-01",
    "start_date": "2026-01-03",
    "units": {
      "D35": {
        "avg_call_duration_mins": 25.05,
        "highest_call_duration_mins": 192.75,
        "single_shift_max_after_midnight": 3,
        "single_shift_max_calls": 4,
        "total_calls": 44,
        "total_calls_after_midnight": 7
      },
      "E34": {
        "avg_call_duration_mins": 18.79,
        "highest_call_duration_mins": 144.73,
        "single_shift_max_after_midnight": 4,
        "single_shift_max_calls": 14,
        "total_calls": 149,
        "total_calls_after_midnight": 17
      },
      "E35": {
        "avg_call_duration_mins": 16.55,
        "highest_call_duration_mins": 166.48,
        "single_shift_max_after_midnight": 3,
        "single_shift_max_calls": 15,
        "total_calls": 232,
        "total_calls_after_midnight": 35
      },
      "E36": {
        "avg_call_duration_mins": 20.09,
        "highest_call_duration_mins": 231.05,
        "single_shift_max_after_midnight": 3,
        "single_shift_max_calls": 14,
        "total_calls": 200,
        "total_calls_after_midnight": 28
      },
      "LR36": {
        "avg_call_duration_mins": 27.46,
        "highest_call_duration_mins": 193.4,
        "single_shift_max_after_midnight": 1,
        "single_shift_max_calls": 4,
        "total_calls": 57,
        "total_calls_after_midnight": 5
      },
      "R33": {
        "avg_call_duration_mins": 19.88,
        "highest_call_duration_mins": 159.4,
        "single_shift_max_after_midnight": 4,
        "single_shift_max_calls": 16,
        "total_calls": 246,
        "total_calls_after_midnight": 38
      },
      "R34": {
        "avg_call_duration_mins": 18.08,
        "highest_call_duration_mins": 146.72,
        "single_shift_max_after_midnight": 5,
        "single_shift_max_calls": 14,
        "total_calls": 242,
        "total_calls_after_midnight": 41
      },
      "R35": {
        "avg_call_duration_mins": 2.15,
        "highest_call_duration_mins": 10.75,
        "single_shift_max_after_midnight": 0,
        "single_shift_max_calls": 5,
        "total_calls": 5,
        "total_calls_after_midnight": 0
      },
      "S36": {
        "avg_call_duration_mins": 17.02,
        "highest_call_duration_mins": 193.4,
        "single_shift_max_after_midnight": 5,
        "single_shift_max_calls": 12,
        "total_calls": 206,
        "total_calls_after_midnight": 28
      },
      "T33": {
        "avg_call_duration_mins": 18.98,
        "highest_call_duration_mins": 239.87,
        "single_shift_max_after_midnight": 3,
        "single_shift_max_calls": 11,
        "total_calls": 182,
        "total_calls_after_midnight": 21
      }
    }
  },
  "prior_shift": {
    "shift_date": "2026-01-31",
    "units": {
      "E34": {
        "avg_time_on_call_mins": 0.0,
        "calls": 1,
        "calls_after_midnight": 0,
        "highest_time_on_call_mins": 0.0
      },
      "E35": {
        "avg_time_on_call_mins": 19.36,
        "calls": 4,
        "calls_after_midnight": 1,
        "highest_time_on_call_mins": 46.47
      },
      "E36": {
        "avg_time_on_call_mins": 7.99,
        "calls": 9,
        "calls_after_midnight": 2,
        "highest_time_on_call_mins": 19.48
      },
      "LR36": {
        "avg_time_on_call_mins": 11.78,
        "calls": 2,
        "calls_after_midnight": 0,
        "highest_time_on_call_mins": 17.5
      },
      "R33": {
        "avg_time_on_call_mins": 29.42,
        "calls": 10,
        "calls_after_midnight": 4,
        "highest_time_on_call_mins": 67.3
      },
      "R34": {
        "avg_time_on_call_mins": 7.32,
        "calls": 8,
        "calls_after_midnight": 1,
        "highest_time_on_call_mins": 21.53
      },
      "S36": {
        "avg_time_on_call_mins": 15.46,
        "calls": 12,
        "calls_after_midnight": 2,
        "highest_time_on_call_mins": 43.02
      },
      "T33": {
        "avg_time_on_call_mins": 35.45,
        "calls": 7,
        "calls_after_midnight": 2,
        "highest_time_on_call_mins": 78.78
      }
    }
  },
  "shift_hour_local": 7,
  "timezone": "Eastern Standard Time",
  "today": {
    "shift_date": "2026-02-01",
    "units": {
      "D35": {
        "avg_time_on_call_mins": 17.48,
        "calls": 1,
        "calls_after_midnight": 0,
        "highest_time_on_call_mins": 17.48
      },
      "E34": {
        "avg_time_on_call_mins": 26.58,
        "calls": 2,
        "calls_after_midnight": 0,
        "highest_time_on_call_mins": 31.6
      },
      "E35": {
        "avg_time_on_call_mins": 0.0,
        "calls": 2,
        "calls_after_midnight": 0,
        "highest_time_on_call_mins": 0.0
      },
      "E36": {
        "avg_time_on_call_mins": 0.0,
        "calls": 1,
        "calls_after_midnight": 0,
        "highest_time_on_call_mins": 0.0
      },
      "LR36": {
        "avg_time_on_call_mins": 18.82,
        "calls": 1,
        "calls_after_midnight": 0,
        "highest_time_on_call_mins": 18.8
      },
      "R33": {
        "avg_time_on_call_mins": 31.83,
        "calls": 3,
        "calls_after_midnight": 0,
        "highest_time_on_call_mins": 30.28
      },
      "S36": {
        "avg_time_on_call_mins": 21.5,
        "calls": 1,
        "calls_after_midnight": 0,
        "highest_time_on_call_mins": 21.48
      },
      "T33": {
        "avg_time_on_call_mins": 6.06,
        "calls": 1,
        "calls_after_midnight": 0,
        "highest_time_on_call_mins": 6.05
      }
    }
  },
  "week": {
    "end_date": "2026-02-01",
    "start_date": "2026-01-26",
    "units": {
      "D35": {
        "avg_call_duration_mins": 17.28,
        "highest_call_duration_mins": 45.1,
        "single_shift_max_after_midnight": 1,
        "single_shift_max_calls": 4,
        "total_calls": 13,
        "total_calls_after_midnight": 2
      },
      "E34": {
        "avg_call_duration_mins": 18.61,
        "highest_call_duration_mins": 80.13,
        "single_shift_max_after_midnight": 3,
        "single_shift_max_calls": 8,
        "total_calls": 31,
        "total_calls_after_midnight": 5
      },
      "E35": {
        "avg_call_duration_mins": 15.03,
        "highest_call_duration_mins": 92.27,
        "single_shift_max_after_midnight": 3,
        "single_shift_max_calls": 13,
        "total_calls": 55,
        "total_calls_after_midnight": 8
      },
      "E36": {
        "avg_call_duration_mins": 13.02,
        "highest_call_duration_mins": 84.08,
        "single_shift_max_after_midnight": 3,
        "single_shift_max_calls": 13,
        "total_calls": 49,
        "total_calls_after_midnight": 10
      },
      "LR36": {
        "avg_call_duration_mins": 16.15,
        "highest_call_duration_mins": 69.42,
        "single_shift_max_after_midnight": 1,
        "single_shift_max_calls": 3,
        "total_calls": 13,
        "total_calls_after_midnight": 1
      },
      "R33": {
        "avg_call_duration_mins": 23.07,
        "highest_call_duration_mins": 159.4,
        "single_shift_max_after_midnight": 4,
        "single_shift_max_calls": 14,
        "total_calls": 73,
        "total_calls_after_midnight": 14
      },
      "R34": {
        "avg_call_duration_mins": 18.57,
        "highest_call_duration_mins": 78.72,
        "single_shift_max_after_midnight": 3,
        "single_shift_max_calls": 11,
        "total_calls": 55,
        "total_calls_after_midnight": 7
      },
      "S36": {
        "avg_call_duration_mins": 17.06,
        "highest_call_duration_mins": 76.6,
        "single_shift_max_after_midnight": 5,
        "single_shift_max_calls": 12,
        "total_calls": 58,
        "total_calls_after_midnight": 12
      },
      "T33": {
        "avg_call_duration_mins": 18.39,
        "highest_call_duration_mins": 84.05,
        "single_shift_max_after_midnight": 2,
        "single_shift_max_calls": 11,
        "total_calls": 51,
        "total_calls_after_midnight": 7
      }
    }
  },
  "year": {
    "end_date": "2026-02-01",
    "start_date": "2025-02-02",
    "units": {
      "D35": {
        "avg_call_duration_mins": 19.58,
        "highest_call_duration_mins": 192.75,
        "single_shift_max_after_midnight": 3,
        "single_shift_max_calls": 6,
        "total_calls": 113,
        "total_calls_after_midnight": 16
      },
      "E33": {
        "avg_call_duration_mins": 0.75,
        "highest_call_duration_mins": 0.73,
        "single_shift_max_after_midnight": 0,
        "single_shift_max_calls": 1,
        "total_calls": 1,
        "total_calls_after_midnight": 0
      },
      "E34": {
        "avg_call_duration_mins": 16.8,
        "highest_call_duration_mins": 144.73,
        "single_shift_max_after_midnight": 6,
        "single_shift_max_calls": 14,
        "total_calls": 405,
        "total_calls_after_midnight": 45
      },
      "E35": {
        "avg_call_duration_mins": 15.8,
        "highest_call_duration_mins": 166.48,
        "single_shift_max_after_midnight": 5,
        "single_shift_max_calls": 18,
        "total_calls": 575,
        "total_calls_after_midnight": 105
      },
      "E36": {
        "avg_call_duration_mins": 18.43,
        "highest_call_duration_mins": 231.05,
        "single_shift_max_after_midnight": 4,
        "single_shift_max_calls": 14,
        "total_calls": 524,
        "total_calls_after_midnight": 68
      },
      "LR36": {
        "avg_call_duration_mins": 22.42,
        "highest_call_duration_mins": 193.4,
        "single_shift_max_after_midnight": 2,
        "single_shift_max_calls": 7,
        "total_calls": 157,
        "total_calls_after_midnight": 18
      },
      "R33": {
        "avg_call_duration_mins": 19.06,
        "highest_call_duration_mins": 159.4,
        "single_shift_max_after_midnight": 5,
        "single_shift_max_calls": 17,
        "total_calls": 685,
        "total_calls_after_midnight": 99
      },
      "R34": {
        "avg_call_duration_mins": 16.98,
        "highest_call_duration_mins": 210.62,
        "single_shift_max_after_midnight": 5,
        "single_shift_max_calls": 18,
        "total_calls": 687,
        "total_calls_after_midnight": 118
      },
      "R35": {
        "avg_call_duration_mins": 5.54,
        "highest_call_duration_mins": 33.58,
        "single_shift_max_after_midnight": 0,
        "single_shift_max_calls": 5,
        "total_calls": 8,
        "total_calls_after_midnight": 0
      },
      "S36": {
        "avg_call_duration_mins": 16.87,
        "highest_call_duration_mins": 193.4,
        "single_shift_max_after_midnight": 5,
        "single_shift_max_calls": 14,
        "total_calls": 544,
        "total_calls_after_midnight": 67
      },
      "T33": {
        "avg_call_duration_mins": 17.32,
        "highest_call_duration_mins": 239.87,
        "single_shift_max_after_midnight": 4,
        "single_shift_max_calls": 11,
        "total_calls": 422,
        "total_calls_after_midnight": 37
      }
    }
  }
}